proxy_overrides/__init__.py
proxy_overrides/base.py
proxy_overrides/related.py
django_proxy_overrides-0.2.3.dist-info/LICENSE
django_proxy_overrides-0.2.3.dist-info/METADATA
django_proxy_overrides-0.2.3.dist-info/WHEEL
django_proxy_overrides-0.2.3.dist-info/top_level.txt
django_proxy_overrides-0.2.3.dist-info/RECORD
