Metadata-Version: 2.1
Name: django-proxy-overrides
Version: 0.2.3
Summary: Overridable foreign key fields for Proxy models
Home-page: https://github.com/datamade/django-proxy-overrides
Author: Matthew Schinckel
Author-email: matt@schinckel.net
Maintainer: Forest Gregg
Maintainer-email: fgregg@datamade.us
License: UNKNOWN
Platform: UNKNOWN
Classifier: License :: OSI Approved :: BSD License
Classifier: Programming Language :: Python :: 3 :: Only
Classifier: Framework :: Django
Classifier: Topic :: Software Development :: Libraries :: Python Modules
License-File: LICENSE
Requires-Dist: Django
